dotbeat/__init__.py
dotbeat/beattime.py
dotbeat/beattools.py
dotbeat-2.0.2.dist-info/METADATA
dotbeat-2.0.2.dist-info/WHEEL
dotbeat-2.0.2.dist-info/licenses/LICENCE
dotbeat-2.0.2.dist-info/RECORD
