Metadata-Version: 2.4
Name: dotbeat
Version: 2.0.2
Summary: A library for Swatch Internet Time
Project-URL: Homepage, https://dotbeat.oddcell.ca/
Project-URL: Repository, https://github.com/theoddcell/dotbeat
Author-email: TheOddCell <me@oddcell.ca>
License: Unlicence
License-File: LICENCE
Requires-Python: >=3.7
